battlefy/__init__.py
battlefy/models/__init__.py
battlefy/models/organization/__init__.py
battlefy/models/organization/org.py
battlefy/models/organization/orgSearch.py
battlefy/models/tournament/__init__.py
battlefy/models/tournament/match.py
battlefy/models/tournament/stage.py
battlefy/models/tournament/standing.py
battlefy/models/tournament/team.py
battlefy/organization.py
battlefy/tournament.py
battlefy_py-0.6.1.dist-info/LICENSE
battlefy_py-0.6.1.dist-info/METADATA
battlefy_py-0.6.1.dist-info/WHEEL
battlefy_py-0.6.1.dist-info/RECORD
