Metadata-Version: 2.1
Name: battlefy.py
Version: 0.6.1
Summary: A Python Library for Battlefy.com
License: MIT
Author: Vincent Lee
Author-email: vlee@vlee.me.uk
Requires-Python: >=3.11,<4.0
Classifier: License :: OSI Approved :: MIT License
Classifier: Programming Language :: Python :: 3
Classifier: Programming Language :: Python :: 3.11
Classifier: Programming Language :: Python :: 3.12
Requires-Dist: aiohttp (>=3.9.1,<4.0.0)
Requires-Dist: python-dateutil (>=2.8.2,<3.0.0)
